prometheus_pve_exporter-3.7.0.dist-info/licenses/LICENSE
pve_exporter/__init__.py
pve_exporter/__main__.py
pve_exporter/cli.py
pve_exporter/config.py
pve_exporter/http.py
pve_exporter/scrape_metrics.py
pve_exporter/collector/__init__.py
pve_exporter/collector/cluster.py
pve_exporter/collector/node.py
prometheus_pve_exporter-3.7.0.dist-info/METADATA
prometheus_pve_exporter-3.7.0.dist-info/WHEEL
prometheus_pve_exporter-3.7.0.dist-info/entry_points.txt
prometheus_pve_exporter-3.7.0.dist-info/top_level.txt
prometheus_pve_exporter-3.7.0.dist-info/RECORD
