Metadata-Version: 2.4
Name: prometheus-pve-exporter
Version: 3.7.0
Summary: Proxmox VE exporter for the Prometheus monitoring system.
Author-email: Lorenz Schori <lo@znerol.ch>
License: Apache-2.0
Project-URL: Homepage, https://github.com/prometheus-pve/prometheus-pve-exporter
Keywords: prometheus,exporter,network,monitoring,proxmox
Classifier: Development Status :: 3 - Alpha
Classifier: Intended Audience :: Information Technology
Classifier: Intended Audience :: System Administrators
Classifier: Topic :: System :: Monitoring
Classifier: Topic :: System :: Networking :: Monitoring
Classifier: License :: OSI Approved :: Apache Software License
Requires-Python: >=3.9
License-File: LICENSE
Requires-Dist: prometheus_client>=0.0.11
Requires-Dist: proxmoxer
Requires-Dist: pyyaml
Requires-Dist: requests
Requires-Dist: Werkzeug
Requires-Dist: gunicorn
Requires-Dist: paramiko
Requires-Dist: wrapt
Provides-Extra: test
Requires-Dist: pylint; extra == "test"
Requires-Dist: pyflakes; extra == "test"
Dynamic: license-file
